EzPyZ/__init__.py
EzPyZ/column.py
EzPyZ/dataframe.py
EzPyZ/result.py
EzPyZ/t_test.py
EzPyZ/tools/__init__.py
EzPyZ/tools/read_files.py
EzPyZ-0.1.9.dist-info/LICENSE
EzPyZ-0.1.9.dist-info/METADATA
EzPyZ-0.1.9.dist-info/WHEEL
EzPyZ-0.1.9.dist-info/top_level.txt
EzPyZ-0.1.9.dist-info/zip-safe
EzPyZ-0.1.9.dist-info/RECORD
